click/__init__.py
click/_compat.py
click/_termui_impl.py
click/_textwrap.py
click/_utils.py
click/_winconsole.py
click/core.py
click/decorators.py
click/exceptions.py
click/formatting.py
click/globals.py
click/parser.py
click/py.typed
click/shell_completion.py
click/termui.py
click/testing.py
click/types.py
click/utils.py
artefacts_click-0.2.0.dist-info/licenses/LICENSE.txt
artefacts_click-0.2.0.dist-info/WHEEL
artefacts_click-0.2.0.dist-info/METADATA
artefacts_click-0.2.0.dist-info/RECORD
