Metadata-Version: 2.4
Name: artefacts-click
Version: 0.2.0
Summary: Composable command line interface toolkit
Maintainer-email: Pallets <contact@palletsprojects.com>
Requires-Python: >=3.10
License-Expression: BSD-3-Clause
Classifier: Development Status :: 5 - Production/Stable
Classifier: Intended Audience :: Developers
Classifier: Operating System :: OS Independent
Classifier: Programming Language :: Python
Classifier: Typing :: Typed
License-File: LICENSE.txt
Requires-Dist: colorama; platform_system == 'Windows'
Project-URL: Changes, https://click.palletsprojects.com/page/changes/
Project-URL: Chat, https://discord.gg/pallets
Project-URL: Documentation, https://click.palletsprojects.com/
Project-URL: Donate, https://palletsprojects.com/donate
Project-URL: Source, https://github.com/pallets/click/
